{
  "version": "1.0.0",
  "ecosystem": "decide.engine-tools",
  "last_updated": "2026-03-29",
  "total_tools": 40,
  "tools": [
    {
      "id": "code-generator",
      "name": "Code Generator",
      "category": "coders",
      "description": "Generate boilerplate code, project scaffolding, and implementations from specs",
      "use_cases": ["create code", "scaffold projects", "generate boilerplate", "implement features"],
      "token_reduction": "70-80%",
      "speed_improvement": "3-4 weeks → 2 days",
      "integration_points": ["code-reviewer", "spec-builder", "app-generator", "test-runner"],
      "prerequisites": ["clear requirement spec", "target language"],
      "output_formats": ["html", "js", "json", "css"],
      "quality_score": 9.2,
      "metadata_value": "high"
    },
    {
      "id": "code-reviewer",
      "name": "Code Reviewer",
      "category": "coders",
      "description": "Validate code quality, security, and pattern compliance",
      "use_cases": ["validate code", "security review", "pattern checking", "refactor suggestions"],
      "token_reduction": "60-70%",
      "integration_points": ["code-generator", "output-evaluator", "spec-builder"],
      "prerequisites": ["code to review", "quality standards"],
      "quality_score": 8.9,
      "metadata_value": "high"
    },
    {
      "id": "agent-builder",
      "name": "Agent Builder",
      "category": "coders",
      "description": "Build autonomous agents and workflows",
      "use_cases": ["create agents", "build workflows", "automation", "AI coordination"],
      "token_reduction": "75-85%",
      "integration_points": ["code-generator", "workflow-builder", "game-command-center"],
      "quality_score": 9.0,
      "metadata_value": "high"
    },
    {
      "id": "app-generator",
      "name": "App Generator",
      "category": "coders",
      "description": "Generate complete applications from specifications",
      "use_cases": ["build apps", "full-stack scaffolding", "MVP generation"],
      "token_reduction": "80-90%",
      "speed_improvement": "4 weeks → 1-2 days",
      "integration_points": ["code-generator", "code-reviewer", "agent-builder"],
      "quality_score": 9.1,
      "metadata_value": "critical"
    },
    {
      "id": "spec-builder",
      "name": "Spec Builder",
      "category": "coders",
      "description": "Create detailed technical specifications and requirements",
      "use_cases": ["write specs", "requirements gathering", "architecture planning"],
      "token_reduction": "50-60%",
      "integration_points": ["code-generator", "decision-brief", "app-generator"],
      "quality_score": 8.7,
      "metadata_value": "high"
    },
    {
      "id": "prompt-alchemy",
      "name": "Prompt Alchemy",
      "category": "creators",
      "description": "Optimize and refine prompts for maximum effectiveness",
      "use_cases": ["optimize prompts", "improve clarity", "reduce tokens", "enhance outputs"],
      "token_reduction": "40-50%",
      "integration_points": ["script-generator", "all-tools"],
      "quality_score": 8.8,
      "metadata_value": "critical"
    },
    {
      "id": "script-generator",
      "name": "Script Generator",
      "category": "creators",
      "description": "Generate scripts, automations, and procedural content",
      "use_cases": ["create scripts", "automation workflows", "batch processing"],
      "token_reduction": "65-75%",
      "integration_points": ["code-generator", "workflow-builder"],
      "quality_score": 8.6,
      "metadata_value": "medium"
    },
    {
      "id": "multi-source-research",
      "name": "Multi-Source Research",
      "category": "researchers",
      "description": "Synthesize information from multiple sources into cohesive analysis",
      "use_cases": ["research topics", "competitive analysis", "data synthesis"],
      "token_reduction": "55-65%",
      "integration_points": ["student-research", "decision-brief"],
      "quality_score": 8.5,
      "metadata_value": "medium"
    },
    {
      "id": "student-research",
      "name": "Student Research",
      "category": "researchers",
      "description": "Structured research for learning and academic purposes",
      "use_cases": ["academic research", "learning", "study prep"],
      "token_reduction": "50-60%",
      "integration_points": ["multi-source-research", "interview-prep"],
      "quality_score": 8.4,
      "metadata_value": "medium"
    },
    {
      "id": "interview-prep",
      "name": "Interview Prep",
      "category": "learners",
      "description": "Comprehensive interview preparation and coaching",
      "use_cases": ["interview prep", "practice questions", "mock interviews"],
      "token_reduction": "60-70%",
      "integration_points": ["student-research", "decision-brief"],
      "quality_score": 8.7,
      "metadata_value": "medium"
    },
    {
      "id": "decision-brief",
      "name": "Decision Brief",
      "category": "professionals",
      "description": "Create structured decision frameworks and business briefs",
      "use_cases": ["make decisions", "create briefs", "strategic planning"],
      "token_reduction": "45-55%",
      "integration_points": ["spec-builder", "workflow-builder", "sales-dashboard"],
      "quality_score": 8.8,
      "metadata_value": "high"
    },
    {
      "id": "sales-dashboard",
      "name": "Sales Dashboard",
      "category": "professionals",
      "description": "Track and optimize sales metrics and pipelines",
      "use_cases": ["sales tracking", "pipeline management", "forecasting"],
      "token_reduction": "50-60%",
      "integration_points": ["decision-brief", "revenue-forecaster"],
      "quality_score": 8.5,
      "metadata_value": "medium"
    },
    {
      "id": "workflow-builder",
      "name": "Workflow Builder",
      "category": "professionals",
      "description": "Create and optimize automated workflows",
      "use_cases": ["build workflows", "process automation", "tool integration"],
      "token_reduction": "65-75%",
      "integration_points": ["all-tools", "agent-builder", "script-generator"],
      "quality_score": 8.9,
      "metadata_value": "critical"
    },
    {
      "id": "tool-search-discovery",
      "name": "Tool Search Discovery",
      "category": "engine",
      "description": "Find and discover the right tool for any problem",
      "use_cases": ["find tools", "tool recommendation", "problem routing"],
      "token_reduction": "30-40%",
      "integration_points": ["all-tools", "tool-router"],
      "quality_score": 8.6,
      "metadata_value": "critical"
    },
    {
      "id": "output-evaluator",
      "name": "Output Evaluator",
      "category": "engine",
      "description": "Evaluate and validate tool outputs against quality standards",
      "use_cases": ["validate outputs", "quality checking", "compliance verification"],
      "token_reduction": "40-50%",
      "integration_points": ["code-reviewer", "all-tools"],
      "quality_score": 8.7,
      "metadata_value": "high"
    },
    {
      "id": "prompt-compare",
      "name": "Prompt Compare",
      "category": "engine",
      "description": "Compare and analyze different prompts and their outputs",
      "use_cases": ["compare approaches", "optimize prompts", "analyze alternatives"],
      "token_reduction": "35-45%",
      "integration_points": ["prompt-alchemy", "output-evaluator"],
      "quality_score": 8.4,
      "metadata_value": "medium"
    },
    {
      "id": "orchard-engine",
      "name": "Orchard Engine",
      "category": "gaming",
      "description": "Merit-based farming game and progression system",
      "use_cases": ["gamification", "progression tracking", "achievement systems"],
      "token_reduction": "50-60%",
      "integration_points": ["leaderboard-analytics", "player-signup"],
      "quality_score": 8.8,
      "metadata_value": "medium"
    },
    {
      "id": "wings-of-fire-quiz",
      "name": "Wings of Fire Quiz",
      "category": "gaming",
      "description": "Interactive quiz system based on Wings of Fire series",
      "use_cases": ["quizzes", "learning games", "knowledge testing"],
      "token_reduction": "45-55%",
      "quality_score": 8.3,
      "metadata_value": "low"
    },
    {
      "id": "context-packager",
      "name": "Context Packager",
      "category": "engine",
      "description": "Package and optimize context for AI models",
      "use_cases": ["prepare context", "token optimization", "info packaging"],
      "token_reduction": "70-80%",
      "integration_points": ["code-generator", "prompt-alchemy"],
      "quality_score": 8.9,
      "metadata_value": "critical"
    },
    {
      "id": "task-splitter",
      "name": "Task Splitter",
      "category": "engine",
      "description": "Break complex tasks into smaller, manageable subtasks",
      "use_cases": ["decompose problems", "task planning", "workflow optimization"],
      "token_reduction": "55-65%",
      "integration_points": ["workflow-builder", "agent-builder"],
      "quality_score": 8.6,
      "metadata_value": "high"
    },
    {
      "id": "template-vault",
      "name": "Template Vault",
      "category": "engine",
      "description": "Store and retrieve reusable templates and patterns",
      "use_cases": ["access templates", "pattern library", "code reuse"],
      "token_reduction": "75-85%",
      "integration_points": ["code-generator", "all-tools"],
      "quality_score": 8.8,
      "metadata_value": "high"
    },
    {
      "id": "export-studio",
      "name": "Export Studio",
      "category": "creators",
      "description": "Export work in multiple formats and optimize for distribution",
      "use_cases": ["export content", "format conversion", "distribution"],
      "token_reduction": "40-50%",
      "integration_points": ["all-tools"],
      "quality_score": 8.5,
      "metadata_value": "medium"
    },
    {
      "id": "idea-remixer",
      "name": "Idea Remixer",
      "category": "creators",
      "description": "Remix and combine ideas into new creative outputs",
      "use_cases": ["brainstorm", "idea generation", "creative combination"],
      "token_reduction": "45-55%",
      "integration_points": ["prompt-alchemy", "script-generator"],
      "quality_score": 8.4,
      "metadata_value": "medium"
    },
    {
      "id": "revenue-forecaster",
      "name": "Revenue Forecaster",
      "category": "professionals",
      "description": "Project revenue and financial outcomes",
      "use_cases": ["forecast revenue", "financial planning", "projections"],
      "token_reduction": "50-60%",
      "integration_points": ["sales-dashboard", "decision-brief"],
      "quality_score": 8.5,
      "metadata_value": "medium"
    },
    {
      "id": "meeting-cost-calculator",
      "name": "Meeting Cost Calculator",
      "category": "engine",
      "description": "Calculate and optimize meeting costs and efficiency",
      "use_cases": ["cost analysis", "meeting optimization"],
      "token_reduction": "40-50%",
      "quality_score": 8.3,
      "metadata_value": "low"
    },
    {
      "id": "tool-router",
      "name": "Tool Router",
      "category": "meta-engine",
      "description": "Route problems to optimal tools (Meta-Tool)",
      "use_cases": ["decide which tool", "problem routing", "optimal selection"],
      "token_reduction": "60-70%",
      "integration_points": ["all-tools", "tool-search-discovery"],
      "quality_score": 9.0,
      "metadata_value": "critical"
    },
    {
      "id": "tool-factory",
      "name": "Tool Factory",
      "category": "meta-engine",
      "description": "Generate new tools from specifications (Meta-Tool)",
      "use_cases": ["create new tools", "expand ecosystem", "tool scaffolding"],
      "token_reduction": "85-95%",
      "speed_improvement": "3-4 weeks → 2 days",
      "integration_points": ["app-generator", "spec-builder", "code-generator"],
      "quality_score": 9.3,
      "metadata_value": "critical"
    },
    {
      "id": "prompt-optimizer",
      "name": "Prompt Optimizer",
      "category": "meta-engine",
      "description": "Continuously improve prompts across all tools (Meta-Tool)",
      "use_cases": ["optimize prompts", "improve tools", "increase efficiency"],
      "token_reduction": "50-60%",
      "integration_points": ["prompt-alchemy", "all-tools"],
      "quality_score": 8.9,
      "metadata_value": "critical"
    }
  ],
  "integration_matrix": {
    "code-generator": ["code-reviewer", "spec-builder", "app-generator", "context-packager", "template-vault"],
    "workflow-builder": ["all-tools", "agent-builder", "script-generator", "task-splitter"],
    "prompt-alchemy": ["script-generator", "all-tools", "prompt-optimizer"],
    "tool-router": ["all-tools", "tool-search-discovery"],
    "tool-factory": ["app-generator", "spec-builder", "code-generator"],
    "prompt-optimizer": ["prompt-alchemy", "all-tools"]
  },
  "metadata_value_distribution": {
    "critical": ["code-generator", "app-generator", "prompt-alchemy", "workflow-builder", "tool-search-discovery", "context-packager", "template-vault", "tool-router", "tool-factory", "prompt-optimizer"],
    "high": ["code-reviewer", "agent-builder", "spec-builder", "decision-brief", "output-evaluator", "task-splitter"],
    "medium": ["script-generator", "multi-source-research", "student-research", "interview-prep", "sales-dashboard", "prompt-compare", "orchard-engine", "idea-remixer", "revenue-forecaster", "export-studio"],
    "low": ["wings-of-fire-quiz", "meeting-cost-calculator"]
  },
  "token_savings_model": {
    "total_average_reduction": "65-75%",
    "ecosystem_multiplier": "With meta-tools: 85-95% savings",
    "monthly_improvement": "2-3% reduction from metadata compounding",
    "note": "Savings multiply when tools work together; meta-tools amplify efficiency"
  }
}
